profanity_api/PYTHON_VERSIONS.json
profanity_api/__init__.py
profanity_api-0.1.0.dist-info/LICENSE
profanity_api-0.1.0.dist-info/METADATA
profanity_api-0.1.0.dist-info/WHEEL
profanity_api-0.1.0.dist-info/top_level.txt
profanity_api-0.1.0.dist-info/RECORD
